{
  "gameInstallPath": "D:\\Games\\S.T.A.L.K.E.R. Shadow of Chernobyl",
  "profiles": [
    {
      "id": "zona-pokayaniya",
      "name": "Zona pokayaniya",
      "description": "OGSR-based test profile",
      "isEnabled": true,
      "launchArguments": "-nointro",
      "executableRelativePath": "bin_x64\\xrEngine.exe",
      "workspacePath": "D:\\StalkerModLauncher\\Workspaces\\Zona-pokayaniya",
      "configNotes": "Profile-specific notes and future config can live here.",
      "mods": [
        {
          "id": "zona-pokayaniya-main",
          "name": "Zona pokayaniya",
          "sourcePath": "D:\\Games\\Mods\\Zona_pokayaniya",
          "isEnabled": true,
          "order": 1,
          "notes": "Main mod folder"
        }
      ]
    }
  ]
}
